<?xml version="1.0" encoding="UTF-8" standalone="yes"?><ns1:Envelope xmlns:ns1="http://vmware.com/vds/envelope/1"><ns1:References><ns1:File ns1:id="file0" ns1:href="data/50 09 c3 b1 1d d4 2f 00-fb d3 59 f3 99 49 9c dd.bak"/><ns1:File ns1:id="file1" ns1:href="data/dvportgroup-31.bak"/><ns1:File ns1:id="file2" ns1:href="data/dvportgroup-30.bak"/><ns1:File ns1:id="file3" ns1:href="data/dvportgroup-33.bak"/><ns1:File ns1:id="file4" ns1:href="data/dvportgroup-32.bak"/><ns1:File ns1:id="file5" ns1:href="data/dvportgroup-34.bak"/></ns1:References><ns1:AnnotationSection><ns1:Annotation></ns1:Annotation><ns1:CreateTime>2020-09-08T23:31:54.158Z</ns1:CreateTime></ns1:AnnotationSection><ns1:DistributedSwitchSection><ns1:DistributedSwitch ns1:id="dvs-29" ns1:fileRef="file0" ns1:name="fabric" ns1:uuid="50 09 c3 b1 1d d4 2f 00-fb d3 59 f3 99 49 9c dd" ns1:configVersion="110" ns1:numberOfUplinks="4" ns1:numberOfResourcePools="0" ns1:numberOfLags="0" ns1:version="7.0.0"/></ns1:DistributedSwitchSection><ns1:VlanSection><ns1:VlanAccess ns1:id="access_302" ns1:vlan="302"/><ns1:VlanAccess ns1:id="access_0" ns1:vlan="0"/><ns1:VlanAccess ns1:id="access_303" ns1:vlan="303"/><ns1:VlanTrunk ns1:id="trunk_0-4094_"><ns1:VlanTrunkRange ns1:start="0" ns1:end="4094"/></ns1:VlanTrunk></ns1:VlanSection><ns1:DistributedPortGroupSection><ns1:DistributedPortGroup ns1:id="dvportgroup-31" ns1:name="pg-trunk" ns1:configVersion="0" ns1:fileRef="file1" ns1:type="standard" ns1:binding="static" ns1:allocation="elastic" ns1:vlanRef="trunk_0-4094_"/><ns1:DistributedPortGroup ns1:id="dvportgroup-30" ns1:name="fabric-uplinks" ns1:configVersion="15" ns1:fileRef="file2" ns1:type="uplink" ns1:binding="static" ns1:allocation="fixed" ns1:vlanRef="trunk_0-4094_"/><ns1:DistributedPortGroup ns1:id="dvportgroup-33" ns1:name="pg-vmotion" ns1:configVersion="3" ns1:fileRef="file3" ns1:type="standard" ns1:binding="static" ns1:allocation="elastic" ns1:vlanRef="access_302"/><ns1:DistributedPortGroup ns1:id="dvportgroup-32" ns1:name="pg-mgmt" ns1:configVersion="0" ns1:fileRef="file4" ns1:type="standard" ns1:binding="static" ns1:allocation="elastic" ns1:vlanRef="access_0"/><ns1:DistributedPortGroup ns1:id="dvportgroup-34" ns1:name="pg-vsan" ns1:configVersion="0" ns1:fileRef="file5" ns1:type="standard" ns1:binding="static" ns1:allocation="elastic" ns1:vlanRef="access_303"/></ns1:DistributedPortGroupSection></ns1:Envelope>